fe_manager/__init__.py
fe_manager/templatetags/__init__.py
fe_manager/templatetags/fe_manager.py
fe_manager/utils/__init__.py
fe_manager/utils/fe_modules_load.py
fe_manager/utils/topological_sorter.py
django_fe_manager-0.0.2.dist-info/LICENSE
django_fe_manager-0.0.2.dist-info/METADATA
django_fe_manager-0.0.2.dist-info/WHEEL
django_fe_manager-0.0.2.dist-info/top_level.txt
django_fe_manager-0.0.2.dist-info/RECORD
