Metadata-Version: 2.1
Name: django-fe-manager
Version: 0.0.2
Summary: Manage front end dependencies in Django.
Home-page: https://gitlab.com/antoniovazquezblanco/django-fe-manager/
Author: Antonio Vázquez Blanco
Author-email: antoniovazquezblanco@gmail.com
License: MIT license
Platform: UNKNOWN
Classifier: Development Status :: 1 - Planning
Classifier: Framework :: Django
Classifier: Intended Audience :: Developers
Classifier: License :: OSI Approved :: MIT License
Classifier: Programming Language :: Python
Classifier: Programming Language :: Python :: 3.7
Classifier: Topic :: Software Development :: Libraries :: Python Modules
Requires: django (>= 2.0)
